{
"title":"ABCDEV 4row",
"onScreen":{
"main":[
"abcdevwxyz",
"fgh[SPACE][][]ijk",
"lmnopqrstu",
"[TOOL][SHIFT][ALTGR:,][SYM:.][123:[ENTER]][4D:'[DEL][WDEL][FDEL]][]"
],

"sym":[
"£¥€$₹^&*()№√÷",
"~`{}%_-=|+§∷‡",
"@[]#/\\'\"«»—‐–",
"…<>!;:?‹›±.,",
"[LOCK][ALTGR:,][SPACE][][][SYM:.][ENTER]"
],

"altGr":[
"ˉˋˇ´¨˙˚¸﹐˛˘˜ˆ",
"―∑éə®†Ωœøπ•·¡",
"æß∂ðƒ©ªº∆≠℥∞¿",
"ʒΩ≈çþ∫ŋµ≤≥°",
"[LOCK][ALTGR:,][SPACE][][][SYM:.][ENTER]"
],

"shifted":[
"ABCDEVWXYZ",
"FGH[SPACE][][]IJK",
"LMNOPQRSTU",
"[LOCK][SHIFT][ALTGR:/][SYM:\\][123:[ENTER]][4D::[DEL][WDEL][FDEL]][]"
]
}
}
    
